multifunctional/__init__.py
multifunctional/allocation.py
multifunctional/custom_allocation.py
multifunctional/database.py
multifunctional/edge_classes.py
multifunctional/errors.py
multifunctional/node_classes.py
multifunctional/node_dispatch.py
multifunctional/supplemental.py
multifunctional/utils.py
multifunctional-1.0.dist-info/LICENSE
multifunctional-1.0.dist-info/METADATA
multifunctional-1.0.dist-info/WHEEL
multifunctional-1.0.dist-info/top_level.txt
multifunctional-1.0.dist-info/RECORD
