Metadata-Version: 2.1
Name: multifunctional
Version: 1.0
Summary: Code for handling multifunctional activities in Brightway
Author-email: Chris Mutel <cmutel@gmail.com>
Maintainer-email: Chris Mutel <cmutel@gmail.com>
Project-URL: source, https://github.com/brightway-lca/multifunctional
Project-URL: homepage, https://github.com/brightway-lca/multifunctional
Project-URL: tracker, https://github.com/brightway-lca/multifunctional/issues
Classifier: Development Status :: 4 - Beta
Classifier: Programming Language :: Python
Classifier: Programming Language :: Python :: 3
Classifier: Programming Language :: Python :: 3.9
Classifier: Programming Language :: Python :: 3.10
Classifier: Programming Language :: Python :: 3.11
Classifier: Programming Language :: Python :: 3.12
Classifier: Natural Language :: English
Classifier: Operating System :: OS Independent
Classifier: Topic :: Scientific/Engineering
Requires-Python: >=3.9
License-File: LICENSE
Requires-Dist: blinker
Requires-Dist: bw2data>=4.0.dev57
Requires-Dist: bw2io>=0.9.dev35
Requires-Dist: bw_processing>=0.9.6
Requires-Dist: numpy<2
Requires-Dist: loguru
Provides-Extra: testing
Requires-Dist: multifunctional; extra == "testing"
Requires-Dist: bw2calc>=2.0.dev17; extra == "testing"
Requires-Dist: pytest; extra == "testing"
Requires-Dist: pytest-cov; extra == "testing"
Requires-Dist: pytest-loguru; extra == "testing"
Requires-Dist: python-coveralls; extra == "testing"
Provides-Extra: dev
Requires-Dist: build; extra == "dev"
Requires-Dist: pre-commit; extra == "dev"
Requires-Dist: pylint; extra == "dev"
Requires-Dist: pytest; extra == "dev"
Requires-Dist: pytest-cov; extra == "dev"
Requires-Dist: pytest-randomly; extra == "dev"
Requires-Dist: setuptools; extra == "dev"
